pykvm/__init__.py
pykvm/kvm.py
pykvm/kvm_types.py
pykvm-1.0.6.dist-info/LICENSE
pykvm-1.0.6.dist-info/METADATA
pykvm-1.0.6.dist-info/WHEEL
pykvm-1.0.6.dist-info/entry_points.txt
pykvm-1.0.6.dist-info/top_level.txt
pykvm-1.0.6.dist-info/RECORD
