Metadata-Version: 2.1
Name: pykvm
Version: 1.0.6
Summary: A KVM client written in Python
Home-page: http://s2e.systems
Author: Vitaly Chipounov
Author-email: vitaly@cyberhaven.io
License: UNKNOWN
Download-URL: https://github.com/S2E/pykvm.git
Platform: UNKNOWN
Classifier: Intended Audience :: Developers
Classifier: Environment :: Console
Classifier: Programming Language :: Python
Classifier: Topic :: Security
Classifier: Topic :: Software Development
Classifier: Topic :: System
Requires-Dist: ioctl-opt
Requires-Dist: hexdump
